mt_to_hugo_article_converter/__init__.py
mt_to_hugo_article_converter/__main__.py
mt_to_hugo_article_converter/converter.py
mt_to_hugo_article_converter/main.py
mt_to_hugo_article_converter/config/__init__.py
mt_to_hugo_article_converter/config/config.py
mt_to_hugo_article_converter/config/validator.py
mt_to_hugo_article_converter/converter/__init__.py
mt_to_hugo_article_converter/converter/converter.py
mt_to_hugo_article_converter/markdown/__init__.py
mt_to_hugo_article_converter/markdown/asset_downloader.py
mt_to_hugo_article_converter/markdown/taxonomies_mapper.py
mt_to_hugo_article_converter/markdown/writer.py
mt_to_hugo_article_converter/mt/__init__.py
mt_to_hugo_article_converter/mt/article.py
mt_to_hugo_article_converter/mt/attribute/__init__.py
mt_to_hugo_article_converter/mt/attribute/attribute.py
mt_to_hugo_article_converter/mt/attribute/author.py
mt_to_hugo_article_converter/mt/attribute/basename.py
mt_to_hugo_article_converter/mt/attribute/body.py
mt_to_hugo_article_converter/mt/attribute/category.py
mt_to_hugo_article_converter/mt/attribute/date.py
mt_to_hugo_article_converter/mt/attribute/extended_body.py
mt_to_hugo_article_converter/mt/attribute/keywords.py
mt_to_hugo_article_converter/mt/attribute/multi_line_attribute.py
mt_to_hugo_article_converter/mt/attribute/primary_category.py
mt_to_hugo_article_converter/mt/attribute/single_line_attribute.py
mt_to_hugo_article_converter/mt/attribute/status.py
mt_to_hugo_article_converter/mt/attribute/tags.py
mt_to_hugo_article_converter/mt/attribute/title.py
mt_to_hugo_article_converter-0.0.5.dist-info/LICENSE
mt_to_hugo_article_converter-0.0.5.dist-info/METADATA
mt_to_hugo_article_converter-0.0.5.dist-info/WHEEL
mt_to_hugo_article_converter-0.0.5.dist-info/entry_points.txt
mt_to_hugo_article_converter-0.0.5.dist-info/top_level.txt
mt_to_hugo_article_converter-0.0.5.dist-info/RECORD
