Metadata-Version: 2.1
Name: mt-to-hugo-article-converter
Version: 0.0.5
Summary: Convert articles from MT to Hugo
Home-page: https://github.com/mazgi/mt-to-hugo-article-converter
Author: Hidenori MATSUKI
Author-email: dev@mazgi.com
License: UNKNOWN
Platform: UNKNOWN
Classifier: Programming Language :: Python :: 3
Classifier: License :: OSI Approved :: MIT License
Classifier: Topic :: Text Processing
Requires-Python: >=3.6
Requires-Dist: python-dateutil
Requires-Dist: pytz
Requires-Dist: pyyaml
